submit/__init__.py
submit/diff_render.py
submit/diff_unit.py
submit/exceptions.py
submit/helpers.py
submit/layout.py
submit/models.py
submit/panels.py
submit/security.py
submit/views.py
submit/migrations/env.py
submit/migrations/versions/124fff07cbcb_use_email_as_usernam.py
submit/migrations/versions/133e975c3ad7_add_timezone_informa.py
submit/migrations/versions/157166237cc7_add_hide_expected_fl.py
submit/migrations/versions/15e554bd88aa_add_deadline_field_t.py
submit/migrations/versions/1cf84ddb034c_clear_out_matching_d.py
submit/migrations/versions/29c521f4449c_add_expected_file_so.py
submit/migrations/versions/2a3f02244cb4_add_consent_date_field_to_user_accounts.py
submit/migrations/versions/2aa111418585_add_is_locked_attrib.py
submit/migrations/versions/2aa8c8ea9d62_add_is_ready_field_t.py
submit/migrations/versions/2ad667bb4592_add_delay_minutes_to.py
submit/migrations/versions/2afd7cb1c8b7_explicitly_set_nulla.py
submit/migrations/versions/305b60854a99_add_points_to_testab.py
submit/migrations/versions/32da2a33a6cc_add_status_field_to_.py
submit/migrations/versions/32e8060589b8_add_missing_indexes.py
submit/migrations/versions/344c3f86394c_add_is_locked_field_.py
submit/migrations/versions/34ac45196731_add_maximum_group_me.py
submit/migrations/versions/385c579612dd_give_many_to_many_ta.py
submit/migrations/versions/38b07be99394_remove_projectview_table.py
submit/migrations/versions/39a5823a808_add_grouprequest_tab.py
submit/migrations/versions/41dda8349f27_add_copy_to_executio.py
submit/migrations/versions/49bc0cea7873_added_points_and_poi.py
submit/migrations/versions/4ae1e9a2ff2_alter_project_delay_minutes_default.py
submit/migrations/versions/4d7019b218d4_refactor_make_proces.py
submit/migrations/versions/4f99b161d06c_add_output_limit_exc.py
submit/migrations/versions/520ecfd63df2_add_warning_regex.py
submit/migrations/versions/525162a280bd_add_is_hidden_to_tes.py
submit-1.2.0.dist-info/DESCRIPTION.rst
submit-1.2.0.dist-info/METADATA
submit-1.2.0.dist-info/RECORD
submit-1.2.0.dist-info/WHEEL
submit-1.2.0.dist-info/entry_points.txt
submit-1.2.0.dist-info/metadata.json
submit-1.2.0.dist-info/top_level.txt
