Metadata-Version: 2.0
Name: submit
Version: 1.2.0
Summary: submit is a submission web service designed for programming assignments
Home-page: https://github.com/ucsb-cs/submit
Author: Bryce Boe
Author-email: bboe@cs.ucsb.edu
License: Simplified BSD License
Keywords: web pyramid pylons
Platform: UNKNOWN
Classifier: Programming Language :: Python
Classifier: Framework :: Pylons
Classifier: Topic :: Internet :: WWW/HTTP
Classifier: Topic :: Internet :: WWW/HTTP :: WSGI :: Application
Requires-Dist: alembic (>=0.6.3)
Requires-Dist: amqp-worker (>=0.2)
Requires-Dist: diff-match-patch (==20120106)
Requires-Dist: numpy (>=1.8.0)
Requires-Dist: python-ldap (>=2.4.14)
Requires-Dist: pastescript (>=1.7.5)
Requires-Dist: pika (>=0.9.6)
Requires-Dist: pyramid (>=1.5.2)
Requires-Dist: pyramid-addons (>=0.20)
Requires-Dist: pyramid-chameleon (>=0.1)
Requires-Dist: pyramid-exclog (>=0.7)
Requires-Dist: pyramid-layout (>=0.8)
Requires-Dist: pyramid-mailer (>=0.10)
Requires-Dist: pyramid-tm (>=0.5)
Requires-Dist: python-daemon (>=1.5.5)
Requires-Dist: python-dateutil (>=2.1)
Requires-Dist: sqla-mixins (>=0.6)
Requires-Dist: sqlalchemy (>=0.7.8)
Requires-Dist: zope.sqlalchemy (>=0.7.1)
Provides-Extra: dev
Requires-Dist: flake8; extra == 'dev'
Requires-Dist: pyramid-debugtoolbar; extra == 'dev'
Requires-Dist: waitress; extra == 'dev'
Provides-Extra: prod
Requires-Dist: psycopg2; extra == 'prod'
Requires-Dist: uwsgi (>=1.2.4); extra == 'prod'
